Metadata-Version: 2.1
Name: doupand
Version: 1.0.5
Summary: A simple and easy-to-use financial data interface library built for normal investors!
Home-page: https://doupand.com
Author: DouBro
Author-email: doupand@163.com
License: BSD
Keywords: Financial Data Interface
Platform: all
Classifier: Development Status :: 4 - Beta
Classifier: Programming Language :: Python :: 2.6
Classifier: Programming Language :: Python :: 2.7
Classifier: Programming Language :: Python :: 3.2
Classifier: Programming Language :: Python :: 3.3
Classifier: Programming Language :: Python :: 3.4
Classifier: Programming Language :: Python :: 3.5
Classifier: License :: OSI Approved :: BSD License
License-File: LICENSE
